riscv/I_O/VALUE_STORAGE/VALUE_STORAGE.sv
typedef enum logic [1:0] {
    WATING_BUTTON_INPUT,
    WATING_BUTTON_UP,

    OUTPUT,
    WATING_OUTPUT
} VALUE_STORAGE_STATE;

module VALUE_STORAGE (
    input wire clk,

    input wire[3:0] buttons,

    input wire io_input_trigger,
    input wire[7:0] io_input_value,

    input wire io_read_ready_trigger, 

    output wire[7:0] io_output_value,
    output wire io_output_trigger,

    output wire[3:0] leds
);
    logic[7:0] internal_value;
    logic internal_io_output_trigger;
    VALUE_STORAGE_STATE state;

    assign io_output_value = internal_value;
    assign leds = internal_value[3:0];
    assign io_output_trigger = internal_io_output_trigger;

    always_ff @(posedge clk) begin
        if (io_input_trigger) begin 
            internal_value <= io_input_value;
        end else begin
            case(state)
                (WATING_BUTTON_INPUT): begin
                    if (buttons[0]) begin
                        internal_value <= (internal_value << 1) + 1;
                        state <= WATING_BUTTON_UP;
                    end else if (buttons[1]) begin
                        internal_value <= (internal_value << 1);
                        state <= WATING_BUTTON_UP;
                    end else if (buttons[2]) begin
                        internal_value <= 0;
                        state <= WATING_BUTTON_UP;
                    end else if (buttons[3]) begin
                        internal_io_output_trigger <= 1;
                        state <= OUTPUT;
                    end
                end
                (WATING_BUTTON_UP): begin
                    if (!(buttons[0] || buttons[1] || buttons[2] || buttons[3])) begin
                        state <= WATING_BUTTON_INPUT;
                    end
                end
                (OUTPUT): begin
                    internal_io_output_trigger <= 0;
                    state <= WATING_OUTPUT;
                end
                (WATING_OUTPUT): begin
                    if (io_read_ready_trigger) begin
                        state <= WATING_BUTTON_UP;
                    end;
                end
            endcase
        end
    end;

    initial begin
        internal_value = 8'd0;
        internal_io_output_trigger = 1'b0;
        state = WATING_BUTTON_INPUT;
    end;

endmodule;

riscv/I_O/VALUE_STORAGE/VALUE_STORAGE_TEST.sv
module VALUE_STORAGE_TEST();
    logic clk;

    logic[3:0] buttons;

    logic io_input_trigger;
    logic[7:0] io_input_value;

    logic io_read_ready_trigger; 

    wire[7:0] io_output_value;
    wire io_output_trigger;

    logic[3:0] leds;

    int error = 0;

    VALUE_STORAGE dut (
        .clk(clk),
        .buttons(buttons),
        .io_input_trigger(io_input_trigger),
        .io_input_value(io_input_value),
        .io_read_ready_trigger(io_read_ready_trigger),
        .io_output_value(io_output_value),
        .io_output_trigger(io_output_trigger),
        .leds(leds)
    );

    initial begin
        clk = 0;
        forever #5 clk = ~clk;
    end

    initial begin
        $dumpfile("VALUE_STORAGE.vcd");
        $dumpvars(0, VALUE_STORAGE_TEST);

        #5


        buttons = 4'd0;

        io_input_trigger = 1'b0;
        io_input_value = 8'd0;

        io_read_ready_trigger = 1'b1;

        #10
        assert(io_output_value ===  8'd0 && io_output_trigger === 1'b0) else error = error + 1;

        buttons = 4'b0001;
        #20
        assert(io_output_value ===  8'd1 && io_output_trigger === 1'b0) else error = error + 1;

        buttons = 4'b0000;
        #10
        assert(io_output_value ===  8'd1 && io_output_trigger === 1'b0) else error = error + 1;

        buttons = 4'b0010;
        #20
        assert(io_output_value ===  8'd2 && io_output_trigger === 1'b0) else error = error + 1;

        buttons = 4'b0000;
        #10
        assert(io_output_value ===  8'd2 && io_output_trigger === 1'b0) else error = error + 1;

        buttons = 4'b0100;
        #10
        assert(io_output_value ===  8'd0 && io_output_trigger === 1'b0) else error = error + 1;

        buttons = 4'b0001;
        #10
        assert(io_output_value ===  8'd0 && io_output_trigger === 1'b0) else error = error + 1;

        buttons = 4'b0000;
        #10
        assert(io_output_value ===  8'd0 && io_output_trigger === 1'b0) else error = error + 1;

        io_input_trigger = 1'b1;
        io_input_value = 8'd22;
        #10
        assert(io_output_value ===  8'd22 && io_output_trigger === 1'b0) else error = error + 1;

        io_input_trigger = 1'b0;
        io_input_value = 8'd40;
        #10
        assert(io_output_value ===  8'd22 && io_output_trigger === 1'b0) else error = error + 1;

        buttons = 4'b1000;
        io_read_ready_trigger = 1'b0;
        #10
        assert(io_output_value ===  8'd22 && io_output_trigger === 1'b1) else error = error + 1;

        buttons = 4'b0000;
        #10
        assert(io_output_value ===  8'd22 && io_output_trigger === 1'b0) else error = error + 1;

        buttons = 4'b0010;
        #20
        assert(io_output_value ===  8'd22 && io_output_trigger === 1'b0) else error = error + 1;

        io_read_ready_trigger = 1'b1;
        #10
        assert(io_output_value ===  8'd22 && io_output_trigger === 1'b0) else error = error + 1;

        buttons = 4'b0000;
        #10
        assert(io_output_value ===  8'd22 && io_output_trigger === 1'b0) else error = error + 1;

        buttons = 4'b0100;
        #10
        assert(io_output_value ===  8'd0 && io_output_trigger === 1'b0) else error = error + 1;

        #10
        if(error == 0)
            $display("ALL TESTS PASSED");
        else
            $display("TEST FAILED with %0d errors", error);
            
        $finish;
    end

endmodule

riscv/I_O/VALUE_STORAGE/VALUE_STORAGE.vcd
$date
	Sun Mar 30 17:19:01 2025
$end
$version
	Icarus Verilog
$end
$timescale
	1s
$end
$scope module VALUE_STORAGE_TEST $end
$var wire 4 ! leds [3:0] $end
$var wire 8 " io_output_value [7:0] $end
$var wire 1 # io_output_trigger $end
$var reg 4 $ buttons [3:0] $end
$var reg 1 % clk $end
$var reg 1 & io_input_trigger $end
$var reg 8 ' io_input_value [7:0] $end
$var reg 1 ( io_read_ready_trigger $end
$var integer 32 ) error [31:0] $end
$scope module dut $end
$var wire 4 * buttons [3:0] $end
$var wire 1 % clk $end
$var wire 1 & io_input_trigger $end
$var wire 8 + io_input_value [7:0] $end
$var wire 1 # io_output_trigger $end
$var wire 8 , io_output_value [7:0] $end
$var wire 1 ( io_read_ready_trigger $end
$var wire 4 - leds [3:0] $end
$var reg 1 . internal_io_output_trigger $end
$var reg 8 / internal_value [7:0] $end
$var reg 2 0 state [1:0] $end
$upscope $end
$upscope $end
$enddefinitions $end
$comment Show the parameter values. $end
$dumpall
$end
#0
$dumpvars
b0 0
b0 /
0.
b0 -
b0 ,
bx +
bx *
b0 )
x(
bx '
x&
0%
bx $
0#
b0 "
b0 !
$end
#5
1(
b0 '
b0 +
0&
b0 $
b0 *
1%
#10
0%
#15
b1 !
b1 -
b1 0
b1 "
b1 ,
b1 /
1%
b1 $
b1 *
#20
0%
#25
1%
#30
0%
#35
b0 0
1%
b0 $
b0 *
#40
0%
#45
b10 !
b10 -
b1 0
b10 "
b10 ,
b10 /
1%
b10 $
b10 *
#50
0%
#55
1%
#60
0%
#65
b0 0
1%
b0 $
b0 *
#70
0%
#75
b0 !
b0 -
b1 0
b0 "
b0 ,
b0 /
1%
b100 $
b100 *
#80
0%
#85
1%
b1 $
b1 *
#90
0%
#95
b0 0
1%
b0 $
b0 *
#100
0%
#105
b110 !
b110 -
b10110 "
b10110 ,
b10110 /
1%
b10110 '
b10110 +
1&
#110
0%
#115
1%
b101000 '
b101000 +
0&
#120
0%
#125
b10 0
1#
1.
1%
0(
b1000 $
b1000 *
#130
0%
#135
b11 0
0#
0.
1%
b0 $
b0 *
#140
0%
#145
1%
b10 $
b10 *
#150
0%
#155
1%
#160
0%
#165
b1 0
1%
1(
#170
0%
#175
b0 0
1%
b0 $
b0 *
#180
0%
#185
b0 !
b0 -
b1 0
b0 "
b0 ,
b0 /
1%
b100 $
b100 *
