riscv/Register/REGISTER_32_BLOCK_32.sv
module REGISTER_32_BLOCK_32 (
    input wire clk,
    
    input wire reset_trigger,

    input wire [4:0] rs1,
    input wire [4:0] rs2,
    input wire [4:0] rd,

    input wire write_trigger,
    input wire [31:0] write_value,

    output logic [31:0] rs1_value,
    output logic [31:0] rs2_value 
);
    logic [31:0] reg_values [0:31];

    always_ff @(posedge clk or posedge reset_trigger) begin
        if (reset_trigger) begin
            for (int i = 0; i < 32; i++) begin
                reg_values[i] <= 32'b0;
            end
        end else if (write_trigger && rd != 0) begin
            reg_values[rd] <= write_value;
        end
    end

    always_ff @(posedge clk) begin
        rs1_value <= reg_values[rs1];
        rs2_value <= reg_values[rs2];
    end

endmodule

riscv/Register/REGISTER_32_BLOCK_32_TEST.sv
module REGISTER_32_BLOCK_32_TEST();
    logic clk = 0;
    logic reset_trigger;
    logic [4:0] rs1, rs2, rd;
    logic write_trigger;
    logic [31:0] write_value;
    logic [31:0] rs1_value, rs2_value;
    int error = 0;

    REGISTER_32_BLOCK_32 dut (
        .clk(clk),
        .reset_trigger(reset_trigger),
        .rs1(rs1),
        .rs2(rs2),
        .rd(rd),
        .write_trigger(write_trigger),
        .write_value(write_value),
        .rs1_value(rs1_value),
        .rs2_value(rs2_value)
    );

    initial begin
        forever #5 clk = ~clk;
    end

    initial begin
        $dumpfile("REGISTER_32_BLOCK_32.vcd");
        $dumpvars(0, REGISTER_32_BLOCK_32_TEST);

        reset_trigger = 1;
        write_trigger = 0;
        rs1 = 5'd0; rs2 = 5'd1;
        rd   = 5'd0;
        write_value = 32'hFFFFFFFF;
        #10;
        reset_trigger = 0;
        #10;
        assert(rs1_value === 32'b0) else error = error + 1;
        assert(rs2_value === 32'b0) else error = error + 1;

        rd = 5'd0;
        write_value = 32'hDEADBEEF;
        write_trigger = 1;
        rs1 = 5'd0; rs2 = 5'd0;
        #10;
        write_trigger = 0;
        #10;
        assert(rs1_value === 32'b0) else error = error + 1;
        assert(rs2_value === 32'b0) else error = error + 1;

        rd = 5'd3;
        write_value = 32'h12345678;
        write_trigger = 1;
        rs1 = 5'd3; rs2 = 5'd3;
        #10;
        write_trigger = 0;
        #10;
        assert(rs1_value === 32'h12345678) else error = error + 1;
        assert(rs2_value === 32'h12345678) else error = error + 1;

        rd = 5'd10;
        write_value = 32'hABCDEF01;
        write_trigger = 1;
        rs1 = 5'd10; rs2 = 5'd3;
        #10;
        write_trigger = 0;
        #10;
        assert(rs1_value === 32'hABCDEF01) else error = error + 1;
        assert(rs2_value === 32'h12345678) else error = error + 1;

        if(error != 0)
            $display("TEST FAILED: %0d errors", error);
        else
            $display("ALL TESTS PASSED");
            
        $finish;
    end

endmodule

riscv/Register/REGISTER_32_BLOCK_32.vcd
$date
	Sat Mar 29 17:32:05 2025
$end
$version
	Icarus Verilog
$end
$timescale
	1s
$end
$scope module REGISTER_32_BLOCK_32_TEST $end
$var wire 32 ! rs2_value [31:0] $end
$var wire 32 " rs1_value [31:0] $end
$var reg 1 # clk $end
$var reg 5 $ rd [4:0] $end
$var reg 1 % reset_trigger $end
$var reg 5 & rs1 [4:0] $end
$var reg 5 ' rs2 [4:0] $end
$var reg 1 ( write_trigger $end
$var reg 32 ) write_value [31:0] $end
$var integer 32 * error [31:0] $end
$scope module dut $end
$var wire 1 # clk $end
$var wire 5 + rd [4:0] $end
$var wire 1 % reset_trigger $end
$var wire 5 , rs1 [4:0] $end
$var wire 5 - rs2 [4:0] $end
$var wire 1 ( write_trigger $end
$var wire 32 . write_value [31:0] $end
$var reg 32 / rs1_value [31:0] $end
$var reg 32 0 rs2_value [31:0] $end
$scope begin $ivl_for_loop0 $end
$var integer 32 1 i [31:0] $end
$upscope $end
$upscope $end
$upscope $end
$enddefinitions $end
$comment Show the parameter values. $end
$dumpall
$end
#0
$dumpvars
b100000 1
bx 0
bx /
b11111111111111111111111111111111 .
b1 -
b0 ,
b0 +
b0 *
b11111111111111111111111111111111 )
0(
b1 '
b0 &
1%
b0 $
0#
bx "
bx !
$end
#5
b0 !
b0 0
b0 "
b0 /
b100000 1
1#
#10
0#
0%
#15
1#
#20
0#
b0 '
b0 -
1(
b11011110101011011011111011101111 )
b11011110101011011011111011101111 .
#25
1#
#30
0#
0(
#35
1#
#40
0#
b11 '
b11 -
b11 &
b11 ,
1(
b10010001101000101011001111000 )
b10010001101000101011001111000 .
b11 $
b11 +
#45
1#
#50
0#
0(
#55
b10010001101000101011001111000 !
b10010001101000101011001111000 0
b10010001101000101011001111000 "
b10010001101000101011001111000 /
1#
#60
0#
b1010 &
b1010 ,
1(
b10101011110011011110111100000001 )
b10101011110011011110111100000001 .
b1010 $
b1010 +
#65
b0 "
b0 /
1#
#70
0#
0(
#75
b10101011110011011110111100000001 "
b10101011110011011110111100000001 /
1#
