riscv/I_O/OUTPUT_CONTROLLER/I_O_OUTPUT_CONTROLLER.sv
typedef enum logic [1:0] {
    OUT_WATING_VALUE,
    OUT_START_SIGNAL,
    OUT_VALUE,
    OUT_END_SIGNAL
} OUTPUT_CONTROLLER_STATE;

module I_O_OUTPUT_CONTROLLER(
  input wire clk,

  input wire[7:0] io_output_value,
  input wire io_output_trigger,

  input wire active,

  output wire io_output_ready_trigger, 
  output wire RXD
);
  logic internal_output;
  logic internal_io_output_ready_trigger;
  logic[2:0] internal_output_counter;
  logic[7:0] internal_current_value;

  OUTPUT_CONTROLLER_STATE internal_state;

  assign RXD = internal_output;
  assign io_output_ready_trigger = internal_io_output_ready_trigger;

  always_ff @(posedge clk) begin
    if (OUT_WATING_VALUE == internal_state && io_output_trigger) begin
      internal_current_value <= io_output_value;
      internal_io_output_ready_trigger <= 0;
      internal_state <= OUT_START_SIGNAL;
      internal_output_counter <= 0;
    end else if (active) begin
      if (internal_state == OUT_START_SIGNAL) begin
        internal_output <= 0;
        internal_state <= OUT_VALUE;
      end else if (internal_state == OUT_VALUE) begin
        internal_output <= internal_current_value[0];
        internal_current_value <= internal_current_value >> 1;
        internal_output_counter <= internal_output_counter + 1;
        if (internal_output_counter == 7) begin
          internal_state <= OUT_END_SIGNAL;
        end
      end else begin
        internal_state <= OUT_WATING_VALUE;
        internal_io_output_ready_trigger <= 1;
        internal_output <= 1;
      end
    end
  end

  initial begin
    internal_output = 1;
    internal_output_counter = 0;
    internal_state = OUT_WATING_VALUE;
    internal_io_output_ready_trigger = 1;
  end;
endmodule;

riscv/I_O/OUTPUT_CONTROLLER/I_O_OUTPUT_CONTROLLER_TEST.sv
module I_O_OUTPUT_CONTROLLER_TEST();
  logic clk;
  logic [7:0] io_output_value;
  logic io_output_trigger;
  logic active;
  logic io_output_ready_trigger;
  logic RXD;
  int error = 0;

  I_O_OUTPUT_CONTROLLER dut (
    .clk(clk),
    .io_output_value(io_output_value),
    .io_output_trigger(io_output_trigger),
    .active(active),
    .io_output_ready_trigger(io_output_ready_trigger),
    .RXD(RXD)
  );

  initial begin
    clk = 0;
    forever #5 clk = ~clk;
  end

  logic [1:0] active_counter;
  initial active_counter = 0;
  always_ff @(posedge clk) begin
    if (active_counter == 3)
      active_counter <= 0;
    else
      active_counter <= active_counter + 1;
  end
  assign active = (active_counter == 0);

  initial begin
    $dumpfile("I_O_OUTPUT_CONTROLLER.vcd");
    $dumpvars(0, I_O_OUTPUT_CONTROLLER_TEST);
    io_output_value = 8'd0;
    io_output_trigger = 1'b0;
    #20;
    assert(io_output_ready_trigger === 1 && RXD === 1) else error = error + 1;
    io_output_value = 8'hAA;
    io_output_trigger = 1'b1;
    #10;
    io_output_trigger = 1'b0;
    #40;
    assert(RXD === 0 && io_output_ready_trigger === 0) else error = error + 1;
    #40;
    assert(RXD === 0 && io_output_ready_trigger === 0) else error = error + 1;
    #40;
    assert(RXD === 1 && io_output_ready_trigger === 0) else error = error + 1;
    #40;
    assert(RXD === 0 && io_output_ready_trigger === 0) else error = error + 1;
    #40;
    assert(RXD === 1 && io_output_ready_trigger === 0) else error = error + 1;
    #40;
    assert(RXD === 0 && io_output_ready_trigger === 0) else error = error + 1;
    #40;
    assert(RXD === 1 && io_output_ready_trigger === 0) else error = error + 1;
    #40;
    assert(RXD === 0 && io_output_ready_trigger === 0) else error = error + 1;
    #40;
    assert(RXD === 1 && io_output_ready_trigger === 0) else error = error + 1;
    #40;
    assert(RXD === 1 && io_output_ready_trigger === 1) else error = error + 1;
    #10;
    if(error == 0)
      $display("ALL TESTS PASSED");
    else
      $display("TEST FAILED with %0d errors", error);
    $finish;
  end
endmodule

riscv/I_O/OUTPUT_CONTROLLER/I_O_OUTPUT_CONTROLLER.vcd
$date
	Sun Mar 30 20:43:24 2025
$end
$version
	Icarus Verilog
$end
$timescale
	1s
$end
$scope module I_O_OUTPUT_CONTROLLER_TEST $end
$var wire 1 ! io_output_ready_trigger $end
$var wire 1 " active $end
$var wire 1 # RXD $end
$var reg 2 $ active_counter [1:0] $end
$var reg 1 % clk $end
$var reg 1 & io_output_trigger $end
$var reg 8 ' io_output_value [7:0] $end
$var integer 32 ( error [31:0] $end
$scope module dut $end
$var wire 1 # RXD $end
$var wire 1 " active $end
$var wire 1 % clk $end
$var wire 1 ! io_output_ready_trigger $end
$var wire 1 & io_output_trigger $end
$var wire 8 ) io_output_value [7:0] $end
$var reg 8 * internal_current_value [7:0] $end
$var reg 1 + internal_io_output_ready_trigger $end
$var reg 1 , internal_output $end
$var reg 3 - internal_output_counter [2:0] $end
$var reg 2 . internal_state [1:0] $end
$upscope $end
$upscope $end
$enddefinitions $end
$comment Show the parameter values. $end
$dumpall
$end
#0
$dumpvars
b0 .
b0 -
1,
1+
bx *
b0 )
b0 (
b0 '
0&
0%
b0 $
1#
1"
1!
$end
#5
0"
b1 $
1%
#10
0%
#15
b10 $
1%
#20
0%
1&
b10101010 '
b10101010 )
#25
b1 .
0!
0+
b10101010 *
b11 $
1%
#30
0%
0&
#35
1"
b0 $
1%
#40
0%
#45
b10 .
0#
0,
0"
b1 $
1%
#50
0%
#55
b10 $
1%
#60
0%
#65
b11 $
1%
#70
0%
#75
1"
b0 $
1%
#80
0%
#85
b1 -
b1010101 *
0"
b1 $
1%
#90
0%
#95
b10 $
1%
#100
0%
#105
b11 $
1%
#110
0%
#115
1"
b0 $
1%
#120
0%
#125
b10 -
b101010 *
1#
1,
0"
b1 $
1%
#130
0%
#135
b10 $
1%
#140
0%
#145
b11 $
1%
#150
0%
#155
1"
b0 $
1%
#160
0%
#165
b11 -
b10101 *
0#
0,
0"
b1 $
1%
#170
0%
#175
b10 $
1%
#180
0%
#185
b11 $
1%
#190
0%
#195
1"
b0 $
1%
#200
0%
#205
b100 -
b1010 *
1#
1,
0"
b1 $
1%
#210
0%
#215
b10 $
1%
#220
0%
#225
b11 $
1%
#230
0%
#235
1"
b0 $
1%
#240
0%
#245
b101 -
b101 *
0#
0,
0"
b1 $
1%
#250
0%
#255
b10 $
1%
#260
0%
#265
b11 $
1%
#270
0%
#275
1"
b0 $
1%
#280
0%
#285
b110 -
b10 *
1#
1,
0"
b1 $
1%
#290
0%
#295
b10 $
1%
#300
0%
#305
b11 $
1%
#310
0%
#315
1"
b0 $
1%
#320
0%
#325
b111 -
b1 *
0#
0,
0"
b1 $
1%
#330
0%
#335
b10 $
1%
#340
0%
#345
b11 $
1%
#350
0%
#355
1"
b0 $
1%
#360
0%
#365
b11 .
b0 -
b0 *
1#
1,
0"
b1 $
1%
#370
0%
#375
b10 $
1%
#380
0%
#385
b11 $
1%
#390
0%
#395
1"
b0 $
1%
#400
0%
#405
1!
1+
b0 .
0"
b1 $
1%
#410
0%
#415
b10 $
1%
#420
0%
#425
b11 $
1%
#430
0%
#435
1"
b0 $
1%
