first/first.sv
module bf_register (
    input logic clk,
    input logic reset_trigger,
    input logic write_trigger,
    input logic [7:0] value,
    output logic [7:0] current_value 
);

    logic [7:0] current_value_internal;

    always_ff @(posedge clk or posedge reset_trigger) begin
        if (reset_trigger) begin
            current_value_internal <= 8'b0;
        end else if (write_trigger) begin
            current_value_internal <= value;
        end
    end

    assign current_value = current_value_internal;

endmodule

module NAND(
    input logic a, 
    input logic b,

    output logic y
);
    assign y = ~(a & b);

endmodule

typedef enum logic [1:0] {
    RUN_COMMAND,
    READ_COMMAND,
    READ_VALUE,
    WRITE_VALUE
} global_state;


typedef enum logic [1:0] {
    DEFAULT,
    SEARCH_NEXT,
    SEARCH_BACK
} state_t;

module bf_command_runner(
    input wire clk,

    input wire run_trigger,

    input wire [2:0] current_command,
    input wire [7:0] current_value,

    output reg [15: 0] command_addr,
    output reg [15: 0] cell_addr,

    output reg [7: 0] new_value,
    output reg write_trigger
);
    reg [15: 0] command_addr_internal;
    reg [15: 0] cell_addr_internal;
    reg [7: 0] stack;
    reg write_trigger_internal;
    reg [7: 0] new_value_internal;

    state_t state = DEFAULT;

    initial begin
        command_addr_internal = 0;
        cell_addr_internal = 0;
        stack = 0;
        write_trigger_internal = 0;
        new_value_internal = 0;
    end

    always @(posedge clk) begin
        write_trigger_internal = 0;
        if (run_trigger) begin
        case(state)
        DEFAULT: begin 
            command_addr_internal = command_addr_internal + 1;
            case(current_command)
            3'b000: begin
                new_value_internal = current_value + 1;
                write_trigger_internal = 1;
            end
            3'b001: begin
                new_value_internal = current_value - 1;
                write_trigger_internal = 1;
            end
            3'b010: begin
                if (current_value == 8'b0) begin
                    stack = 0;
                    state = SEARCH_NEXT;
                end
            end
            3'b011: begin
                if (current_value != 8'b0) begin
                    stack = 0;
                    command_addr_internal = command_addr_internal - 2;
                    state = SEARCH_BACK;
                end
            end
            3'b100: begin
                cell_addr_internal = cell_addr_internal + 1;
            end
            3'b101: begin
                cell_addr_internal = cell_addr_internal - 1;
            end
            endcase
        end
        SEARCH_NEXT: begin 
            command_addr_internal = command_addr_internal + 1;
            if (current_command == 3'b011) begin
                if (stack == 0) begin
                    state = DEFAULT;
                end else begin
                    stack = stack - 1;
                end
            end else if (current_command == 3'b010) begin
                stack = stack + 1;
            end
        end
        SEARCH_BACK: begin 
            command_addr_internal = command_addr_internal - 1;
            if (current_command == 3'b010) begin
                if (stack == 0) begin
                    state = DEFAULT;
                    command_addr_internal = command_addr_internal + 2;
                end else begin
                    stack = stack - 1;
                end
            end else if (current_command == 3'b011) begin
                stack = stack + 1;
            end
        end
        endcase 
        end
    end

    assign cell_addr = cell_addr_internal;
    assign command_addr = command_addr_internal;
    assign new_value = new_value_internal;
    assign write_trigger = write_trigger_internal;


endmodule

module memory_model #(
    parameter DATA_WIDTH = 8,
    parameter ADDR_WIDTH = 16
)(
    input  wire                   clk,
    input  wire                   we,       // сигнал записи
    input  wire [ADDR_WIDTH-1:0]  addr,
    input  wire [DATA_WIDTH-1:0]  data_in,
    output reg  [DATA_WIDTH-1:0]  data_out
);

    reg [DATA_WIDTH-1:0] mem [(2**ADDR_WIDTH)-1:0];

    initial begin
        integer i;
        for (i = 0; i < (2**ADDR_WIDTH); i = i + 1)
            mem[i] = 0;
    end

    always @(posedge clk) begin
        if (we)
            mem[addr] <= data_in;
        data_out <= mem[addr];
    end

endmodule

first/first_test.sv
module REG_tb();

    logic clk=0;
    logic reset_trigger;
    logic write_trigger;
    logic [7:0] value;
    logic [7:0] current_value;

    int error=0;

    bf_register dut(clk, reset_trigger, write_trigger, value, current_value); // device under test i.e. the gate we want to test

    initial begin
        $dumpfile("reg.vcd");
        $dumpvars(0, REG_tb);
            
        reset_trigger=0; write_trigger=1; value = 8'b100; #10;
        assert(current_value===8'b100) else error=1;
            
        reset_trigger=0; write_trigger=0; value = 8'b110; #10;
        assert(current_value===8'b100) else error=1;
        
        reset_trigger=1; write_trigger=0; value = 8'b100; #10;
        assert(current_value===8'b0) else error=1;
            
        reset_trigger=0; write_trigger=1; value = 8'b100; #10;
        assert(current_value===8'b100) else error=1;
    end

    initial begin
        for (int i = 0; i < 60; i = i + 1) begin
            #5 clk = ~clk;
        end
    end
    
endmodule

module NAND_tb();

    logic a, b, y;
    int error=0;

    NAND dut(a, b, y); // device under test i.e. the gate we want to test

    initial begin
        $dumpfile("nand.vcd");
        $dumpvars(0, NAND_tb);
            
        a=0; b=0;   #10;
        assert(y===1) else error=1;
            
        b=1;        #10;
        assert(y===1) else error=1;
            
        a=1; b=0;   #10;
        assert(y===1) else error=1;
            
        b=1;        #10;
        assert(y===0) else error=1;
    end
    
    always@(a, b, y, error) begin
        if(!error) begin 
            $display("Time=%Dt inputs:a=%b\t b=%b\t output:y=%b", $time, a, b, y);            
        end else begin
            $error("Test fail at time=%Dt inputs:a=%b\t b=%b\t output:y=%b", $time, a, b, y);
            error=0;      
        end
    end
    
endmodule

module bf_command_runner_tb();

    // Объявление сигналов для тестирования
    logic clk = 0;
    logic run_trigger;
    logic [2:0] current_command;
    logic [7:0] current_value;
    logic [15:0] command_addr;
    logic [15:0] cell_addr;
    logic [7:0] new_value;
    logic        write_trigger;
    
    int error = 0;

    // Инстанцирование устройства под тестированием (DUT)
    bf_command_runner dut(
        .clk(clk),
        .run_trigger(run_trigger),
        .current_command(current_command),
        .current_value(current_value),
        .command_addr(command_addr),
        .cell_addr(cell_addr),
        .new_value(new_value),
        .write_trigger(write_trigger)
    );
    
    // Тестовая последовательность
    initial begin
        $dumpfile("bf_command_runner.vcd");
        $dumpvars(0, bf_command_runner_tb);
        
        // Начальная инициализация сигналов
        run_trigger = 0;
        current_command = 3'b000;
        current_value = 8'd0;
        #10;
        
        // Тест 1: Команда 3'b000 (инкремент значения)
        // Ожидается: new_value = current_value + 1, write_trigger = 1
        run_trigger = 1;
        current_command = 3'b000;
        current_value = 8'd10;
        #10;
        assert(new_value === 16'd11) else begin
            $display("Ошибка: для 3'b000 ожидалось new_value = 11, получено %0d", new_value);
            error = error + 1;
        end
        assert(write_trigger === 1) else begin
            $display("Ошибка: для 3'b000 ожидалось write_trigger = 1, получено %0d", write_trigger);
            error = error + 1;
        end
        
        // Тест 2: Команда 3'b001 (декремент значения)
        // Ожидается: new_value = current_value - 1, write_trigger = 1
        current_command = 3'b001;
        current_value = 8'd20;
        #10;
        assert(new_value === 16'd19) else begin
            $display("Ошибка: для 3'b001 ожидалось new_value = 19, получено %0d", new_value);
            error = error + 1;
        end
        assert(write_trigger === 1) else begin
            $display("Ошибка: для 3'b001 ожидалось write_trigger = 1, получено %0d", write_trigger);
            error = error + 1;
        end
        
        // Тест 3: Команда 3'b010 (переход, если значение равно 0)
        // Ожидается: переход в состояние SEARCH_NEXT, запись не инициируется (write_trigger = 0)
        current_command = 3'b010;
        current_value = 8'd0;
        #10;
        assert(write_trigger === 0) else begin
            $display("Ошибка: для 3'b010 ожидалось write_trigger = 0, получено %0d", write_trigger);
            error = error + 1;
        end
        
        // Тест 4: Команда 3'b011 (переход назад, если значение не равно 0)
        // Ожидается: переход в состояние SEARCH_BACK, запись не инициируется (write_trigger = 0)
        current_command = 3'b011;
        current_value = 8'd5;
        #10;
        assert(write_trigger === 0) else begin
            $display("Ошибка: для 3'b011 ожидалось write_trigger = 0, получено %0d", write_trigger);
            error = error + 1;
        end
        
        // Тест 5: Команда 3'b100 (сдвиг адреса ячейки вправо)
        // Ожидается: увеличение cell_addr
        current_command = 3'b100;
        #10;
        assert(cell_addr === 16'd1) else begin
            $display("Ошибка: для 3'b100 ожидалось cell_addr = 1, получено %0d", cell_addr);
            error = error + 1;
        end
        
        // Тест 6: Команда 3'b101 (сдвиг адреса ячейки влево)
        // Ожидается: уменьшение cell_addr
        current_command = 3'b101;
        #10;
        assert(cell_addr === 16'd0) else begin
            $display("Ошибка: для 3'b101 ожидалось cell_addr = 0, получено %0d", cell_addr);
            error = error + 1;
        end
        
        if(error == 0) begin
            $display("Все тесты пройдены успешно.");
        end else begin
            $display("Обнаружено %0d ошибок.", error);
        end
        $finish;
    end

    // Генерация тактового сигнала: переключение каждые 5 единиц времени
    always begin
        #5 clk = ~clk;
    end

endmodule

first/nand.vcd
$date
	Sun Mar 23 22:36:24 2025
$end
$version
	Icarus Verilog
$end
$timescale
	1s
$end
$scope module NAND_tb $end
$var wire 1 ! y $end
$var reg 1 " a $end
$var reg 1 # b $end
$var integer 32 $ error [31:0] $end
$scope module dut $end
$var wire 1 " a $end
$var wire 1 # b $end
$var wire 1 ! y $end
$upscope $end
$upscope $end
$scope module REG_tb $end
$var wire 8 % current_value [7:0] $end
$var reg 1 & clk $end
$var reg 1 ' reset_trigger $end
$var reg 8 ( value [7:0] $end
$var reg 1 ) write_trigger $end
$var integer 32 * error [31:0] $end
$scope module dut $end
$var wire 1 & clk $end
$var wire 8 + current_value [7:0] $end
$var wire 1 ' reset_trigger $end
$var wire 8 , value [7:0] $end
$var wire 1 ) write_trigger $end
$var reg 8 - current_value_internal [7:0] $end
$upscope $end
$scope begin $ivl_for_loop0 $end
$var integer 32 . i [31:0] $end
$upscope $end
$upscope $end
$scope module bf_command_runner_tb $end
$var wire 1 / write_trigger $end
$var wire 8 0 new_value [7:0] $end
$var wire 16 1 command_addr [15:0] $end
$var wire 16 2 cell_addr [15:0] $end
$var reg 1 3 clk $end
$var reg 3 4 current_command [2:0] $end
$var reg 8 5 current_value [7:0] $end
$var reg 1 6 run_trigger $end
$var integer 32 7 error [31:0] $end
$scope module dut $end
$var wire 16 8 cell_addr [15:0] $end
$var wire 1 3 clk $end
$var wire 16 9 command_addr [15:0] $end
$var wire 3 : current_command [2:0] $end
$var wire 8 ; current_value [7:0] $end
$var wire 8 < new_value [7:0] $end
$var wire 1 6 run_trigger $end
$var wire 1 / write_trigger $end
$var reg 16 = cell_addr_internal [15:0] $end
$var reg 16 > command_addr_internal [15:0] $end
$var reg 8 ? new_value_internal [7:0] $end
$var reg 8 @ stack [7:0] $end
$var reg 2 A state [1:0] $end
$var reg 1 B write_trigger_internal $end
$upscope $end
$upscope $end
$enddefinitions $end
$comment Show the parameter values. $end
$dumpall
$end
#0
$dumpvars
0B
b0 A
b0 @
b0 ?
b0 >
b0 =
b0 <
b0 ;
b0 :
b0 9
b0 8
b0 7
06
b0 5
b0 4
03
b0 2
b0 1
b0 0
0/
b0 .
bx -
b100 ,
bx +
b0 *
1)
b100 (
0'
0&
bx %
b0 $
0#
0"
1!
$end
#5
b100 %
b100 +
b100 -
13
b1 .
1&
#10
03
b10 .
0&
b1010 5
b1010 ;
16
b110 (
b110 ,
0)
1#
#15
1/
1B
b1011 0
b1011 <
b1011 ?
b1 1
b1 9
b1 >
13
b11 .
1&
#20
b0 %
b0 +
b0 -
03
b100 .
0&
b10100 5
b10100 ;
b1 4
b1 :
b100 (
b100 ,
1'
0#
1"
#25
b10011 0
b10011 <
b10011 ?
b10 1
b10 9
b10 >
1/
1B
13
b101 .
1&
#30
0!
03
b110 .
0&
b0 5
b0 ;
b10 4
b10 :
1)
0'
1#
#35
b100 %
b100 +
b100 -
b1 A
b11 1
b11 9
b11 >
0/
0B
13
b111 .
1&
#40
03
b1000 .
0&
b101 5
b101 ;
b11 4
b11 :
#45
b0 A
b100 1
b100 9
b100 >
13
b1001 .
1&
#50
03
b1010 .
0&
b100 4
b100 :
#55
b1 2
b1 8
b1 =
b101 1
b101 9
b101 >
13
b1011 .
1&
#60
03
b1100 .
0&
b101 4
b101 :
#65
b0 2
b0 8
b0 =
b110 1
b110 9
b110 >
13
b1101 .
1&
#70
03
b1110 .
0&
